openelm/__init__.py
openelm/configs.py
openelm/constants.py
openelm/elm.py
openelm/mutation_model.py
openelm/algorithms/__init__.py
openelm/algorithms/genetic.py
openelm/algorithms/map_elites.py
openelm/benchmarks/__init__.py
openelm/benchmarks/benchmark_bugs.py
openelm/benchmarks/benchmark_crossover.py
openelm/benchmarks/benchmark_lm_speed.py
openelm/benchmarks/benchmark_sodarace_parallel.py
openelm/benchmarks/benchmark_tinygp.py
openelm/benchmarks/benchmarks_triton.py
openelm/codegen/__init__.py
openelm/codegen/codegen_triton.py
openelm/codegen/codegen_utilities.py
openelm/codegen/configuration_codegen.py
openelm/codegen/modelling_codegen.py
openelm/codegen/triton_utils/codegen_gptj_converter.py
openelm/codegen/triton_utils/config_template.pbtxt
openelm/codegen/triton_utils/convert_ft.py
openelm/codegen/triton_utils/gptj_ftconverter.py
openelm/codegen/triton_utils/readme.md
openelm/codegen/triton_utils/triton_start.sh
openelm/environments/__init__.py
openelm/environments/base.py
openelm/environments/poetry.py
openelm/environments/utils.py
openelm/environments/p3/__init__.py
openelm/environments/p3/p3.py
openelm/environments/prompt/__init__.py
openelm/environments/prompt/prompt.py
openelm/environments/prompt/utils.py
openelm/environments/prompt/datasets/README.md
openelm/environments/prompt/datasets/annotations/active_to_passive.json
openelm/environments/prompt/datasets/annotations/antonyms.json
openelm/environments/prompt/datasets/annotations/cause_and_effect.json
openelm/environments/prompt/datasets/annotations/common_concept.json
openelm/environments/prompt/datasets/annotations/diff.json
openelm/environments/prompt/datasets/annotations/first_word_letter.json
openelm/environments/prompt/datasets/annotations/informal_to_formal.json
openelm/environments/prompt/datasets/annotations/larger_animal.json
openelm/environments/prompt/datasets/annotations/letters_list.json
openelm/environments/prompt/datasets/annotations/negation.json
OpenELM-0.9.2.dist-info/LICENSE
OpenELM-0.9.2.dist-info/METADATA
OpenELM-0.9.2.dist-info/WHEEL
OpenELM-0.9.2.dist-info/top_level.txt
OpenELM-0.9.2.dist-info/RECORD
