Metadata-Version: 2.1
Name: OpenELM
Version: 0.9.2
Summary: Evolution Through Large Models
Author: CarperAI
License: MIT
Classifier: Development Status :: 3 - Alpha
Classifier: Environment :: Console
Classifier: Intended Audience :: Science/Research
Classifier: Intended Audience :: Developers
Classifier: License :: OSI Approved :: MIT License
Classifier: Natural Language :: English
Classifier: Programming Language :: Python
Classifier: Programming Language :: Python :: 3
Classifier: Programming Language :: Python :: 3.9
Classifier: Programming Language :: Python :: 3.10
Classifier: Programming Language :: Python :: 3 :: Only
Classifier: Programming Language :: Python :: Implementation :: CPython
Classifier: Topic :: Scientific/Engineering :: Artificial Intelligence
Classifier: Typing :: Typed
Classifier: Operating System :: Unix
Requires-Python: >=3.9
License-File: LICENSE
Requires-Dist: hydra-core (>=1.2.0)
Requires-Dist: wandb (>=0.13)
Requires-Dist: numpy
Requires-Dist: torch (>=1.10)
Requires-Dist: transformers (>=4.22.0)
Requires-Dist: tokenizers
Requires-Dist: requests
Requires-Dist: Flask
Requires-Dist: scikit-learn
Requires-Dist: matplotlib
Requires-Dist: langchain (==0.0.225)
Requires-Dist: typing-extensions (==4.5)
Requires-Dist: openai
Requires-Dist: plotly
Provides-Extra: benchmarks
Requires-Dist: pygraphviz ; extra == 'benchmarks'
Requires-Dist: graphviz ; extra == 'benchmarks'
Requires-Dist: openai ; extra == 'benchmarks'
Provides-Extra: dev
Requires-Dist: black ; extra == 'dev'
Requires-Dist: isort ; extra == 'dev'
Requires-Dist: flake8 ; extra == 'dev'
Requires-Dist: flake8-pyproject ; extra == 'dev'
Requires-Dist: pydocstyle ; extra == 'dev'
Requires-Dist: mypy ; extra == 'dev'
Requires-Dist: pre-commit ; extra == 'dev'
Requires-Dist: pytest ; extra == 'dev'
Requires-Dist: pytest-cov ; extra == 'dev'
Provides-Extra: docs
Requires-Dist: sphinx (==5.3.0) ; extra == 'docs'
Requires-Dist: sphinx-rtd-theme ; extra == 'docs'
Requires-Dist: sphinx-autodoc-typehints ; extra == 'docs'
Provides-Extra: notebook
Requires-Dist: ipython ; extra == 'notebook'
Provides-Extra: sodaracer
Requires-Dist: swig (>=4.1.0) ; extra == 'sodaracer'
Requires-Dist: box2d-py (==2.3.8) ; extra == 'sodaracer'
Requires-Dist: pygame ; extra == 'sodaracer'
Provides-Extra: triton
Requires-Dist: tritonclient[all] ; extra == 'triton'
